mvarcs/__init__.py
mvarcs/__main__.py
mvarcs/core.py
mvarcs/mvarcs/cacert.pem
mvarcs-1.0.0.dist-info/licenses/LICENSE
mvarcs-1.0.0.dist-info/METADATA
mvarcs-1.0.0.dist-info/WHEEL
mvarcs-1.0.0.dist-info/top_level.txt
mvarcs-1.0.0.dist-info/RECORD
