Metadata-Version: 2.4
Name: mvarcs
Version: 1.0.0
Summary: Python package for providing the MVA Root Certificates Store
Home-page: https://github.com/markcerts/mvarcs-python
Author: OllieJC
Author-email: mvarcs-pypi@olliejc.uk
License: The Unlicense
Project-URL: Bug Tracker, https://github.com/markcerts/mvarcs-python/issues
Project-URL: MVARCS, https://github.com/markcerts/mvarcs
Keywords: BIMI,VMC,CMC,Verification,Trusted
Classifier: Development Status :: 5 - Production/Stable
Classifier: Intended Audience :: Developers
Classifier: Intended Audience :: System Administrators
Classifier: License :: OSI Approved :: The Unlicense (Unlicense)
Classifier: Programming Language :: Python :: 3
Classifier: Natural Language :: English
Classifier: Operating System :: OS Independent
Classifier: Topic :: Security :: Cryptography
Classifier: Topic :: Utilities
Classifier: Topic :: Software Development :: Libraries :: Python Modules
Requires-Python: >=3.6
License-File: LICENSE
Dynamic: author
Dynamic: author-email
Dynamic: classifier
Dynamic: description
Dynamic: description-content-type
Dynamic: home-page
Dynamic: keywords
Dynamic: license
Dynamic: license-file
Dynamic: project-url
Dynamic: requires-python
Dynamic: summary
